setup.py
navpreet_distributions/Binomialdistribution.py
navpreet_distributions/Gaussiandistribution.py
navpreet_distributions/Generaldistribution.py
navpreet_distributions/__init__.py
navpreet_distributions.egg-info/PKG-INFO
navpreet_distributions.egg-info/SOURCES.txt
navpreet_distributions.egg-info/dependency_links.txt
navpreet_distributions.egg-info/not-zip-safe
navpreet_distributions.egg-info/top_level.txt