Metadata-Version: 1.0
Name: navpreet-distributions
Version: 0.1
Summary: Gaussian distributions
Home-page: UNKNOWN
Author: Navpreet Singh
Author-email: UNKNOWN
License: UNKNOWN
Platform: UNKNOWN
